cityseer-4.22.0.dist-info/METADATA
cityseer-4.22.0.dist-info/WHEEL
cityseer-4.22.0.dist-info/licenses/LICENSE.txt
cityseer.libs/libgcc_s-1e52349c.so.1
cityseer/__init__.py
cityseer/config.py
cityseer/metrics/__init__.py
cityseer/metrics/layers.py
cityseer/metrics/networks.py
cityseer/metrics/observe.py
cityseer/metrics/visibility.py
cityseer/rustalgos.cpython-312-x86_64-linux-musl.so
cityseer/rustalgos/__init__.pyi
cityseer/rustalgos/centrality.pyi
cityseer/rustalgos/data.pyi
cityseer/rustalgos/diversity.pyi
cityseer/rustalgos/graph.pyi
cityseer/rustalgos/viewshed.pyi
cityseer/tools/__init__.py
cityseer/tools/graphs.py
cityseer/tools/io.py
cityseer/tools/mock.py
cityseer/tools/plot.py
cityseer/tools/util.py
cityseer-4.22.0.dist-info/RECORD
