Metadata-Version: 2.4
Name: cityseer
Version: 4.22.0
Classifier: Programming Language :: Python :: 3.11
Classifier: Programming Language :: Python :: 3.12
Classifier: Programming Language :: Python :: 3.13
Classifier: Programming Language :: Rust
Requires-Dist: matplotlib>=3.5.3
Requires-Dist: networkx>=3.0.0
Requires-Dist: pyproj>=3.5.0
Requires-Dist: requests>=2.27.1
Requires-Dist: tqdm>=4.63.2
Requires-Dist: shapely>=2.0.6
Requires-Dist: numpy>=1.26.4
Requires-Dist: geopandas>=1.0.1
Requires-Dist: rasterio>=1.3.9
Requires-Dist: fiona>=1.9.0
Requires-Dist: osmnx>=2.0.1
License-File: LICENSE.txt
Summary: Computational tools for network-based pedestrian-scale urban analysis
Keywords: network-topology,numpy,architecture,openstreetmap,urban-planning,python3,networkx,networks,spatial-analysis,geographical-information-system,spatial-data,morphometrics,network-analysis,momepy,spatial-data-analysis,centrality,shapely,landuse,osmnx,network-centralities
Author-email: Gareth Simons <info@benchmarkurbanism.com>
Maintainer-email: Gareth Simons <info@benchmarkurbanism.com>
License: AGPL-3.0
Requires-Python: >=3.11, <3.14
Project-URL: homepage, https://cityseer.benchmarkurbanism.com/
Project-URL: documentation, https://cityseer.benchmarkurbanism.com/
Project-URL: repository, https://github.com/benchmark-urbanism/cityseer-api
